quandelibc.cpython-310-x86_64-linux-gnu.so
quandelibc-0.6.0.dist-info/LICENSE
quandelibc-0.6.0.dist-info/top_level.txt
quandelibc-0.6.0.dist-info/WHEEL
quandelibc-0.6.0.dist-info/RECORD
quandelibc-0.6.0.dist-info/METADATA
