Metadata-Version: 2.1
Name: quandelibc
Version: 0.6.0
Summary: Optimized C-functions for Perceval
Home-page: https://github.com/Quandela/QuandeLibC
Download-URL: https://github.com/Quandela/QuandeLibC
Author: Perceval.OSS@Quandela.com
Author-email: Perceval.OSS@Quandela.com
Project-URL: Documentation, https://perceval.quandela.net/docs-quandelibc/
Project-URL: Source, https://github.com/Quandela/QuandeLibC
Project-URL: Tracker, https://github.com/Quandela/QuandeLibC/issues
Classifier: Programming Language :: Python :: 3
Classifier: License :: OSI Approved :: MIT License
License-File: LICENSE
Provides-Extra: test
Requires-Dist: pytest ; extra == 'test'
